GUI/FCC_Motor_Control.py
GUI/__init__.py
GUI/widgets/__init__.py
GUI/widgets/daqgraph/__init__.py
GUI/widgets/settingspopup/__init__.py
RTAPlusL5/RTACommands.py
RTAPlusL5/RTAPlusL5.py
RTAPlusL5/SerialComm.py
RTAPlusL5/__init__.py
RTAPlusL5/device_labels.py
RTAPlusL5/load_csv_to_dict.py
RTAPlusL5/logger.py
RTAPlusL5-0.0.6.dist-info/METADATA
RTAPlusL5-0.0.6.dist-info/WHEEL
RTAPlusL5-0.0.6.dist-info/top_level.txt
RTAPlusL5-0.0.6.dist-info/RECORD
