Metadata-Version: 2.1
Name: RTAPlusL5
Version: 0.0.6
Summary: Python Library to interface with RTA Plus L5 motor controller through RS458 interface
Home-page: https://gitlab.pic.es/fcc_control/rta_plus_l5_driver
Author: Oscar Martínez
Author-email: omartinez@ifae.es
License: CC0 1.0 Universal
Classifier: Development Status :: 4 - Beta
Classifier: Programming Language :: Python :: 3
Provides: RTAPlusL5
Requires-Python: >=3
Requires-Dist: pyserial
